aiocheck/Database.py
aiocheck/Host.py
aiocheck/__init__.py
aiocheck/cli/__init__.py
aiocheck/cli/main.py
aiocheck-0.0.11.dist-info/LICENCE
aiocheck-0.0.11.dist-info/METADATA
aiocheck-0.0.11.dist-info/WHEEL
aiocheck-0.0.11.dist-info/entry_points.txt
aiocheck-0.0.11.dist-info/top_level.txt
aiocheck-0.0.11.dist-info/zip-safe
aiocheck-0.0.11.dist-info/RECORD
