Metadata-Version: 2.1
Name: aiocheck
Version: 0.0.11
Summary: A python asyncio host health checker using native ping commands
Home-page: https://github.com/kruserr/aiocheck
Author: kruserr
License: UNKNOWN
Project-URL: Documentation, https://github.com/kruserr/aiocheck/wiki
Project-URL: Source, https://github.com/kruserr/aiocheck
Keywords: asyncio host health checker native ping
Platform: UNKNOWN
Classifier: Topic :: System :: Networking :: Monitoring
Classifier: Development Status :: 4 - Beta
Classifier: Intended Audience :: Developers
Classifier: Intended Audience :: System Administrators
Classifier: Programming Language :: Python :: 3
Classifier: License :: OSI Approved :: MIT License
Classifier: Operating System :: OS Independent
Requires-Python: >=3.7
